pkgcreator/__init__.py
pkgcreator/__main__.py
pkgcreator/builder.py
pkgcreator/cli.py
pkgcreator/cli_tools.py
pkgcreator/file_contents.py
pkgcreator/filetypes.py
pkgcreator/ghutils.py
pkgcreator/gitrepo.py
pkgcreator/logging_tools.py
pkgcreator/venv_manager.py
pkgcreator-0.1.0.post1.dist-info/licenses/LICENSE
pkgcreator-0.1.0.post1.dist-info/METADATA
pkgcreator-0.1.0.post1.dist-info/WHEEL
pkgcreator-0.1.0.post1.dist-info/entry_points.txt
pkgcreator-0.1.0.post1.dist-info/top_level.txt
pkgcreator-0.1.0.post1.dist-info/RECORD
