Metadata-Version: 2.4
Name: pkgcreator
Version: 0.1.0.post1
Summary: Create python package structure, necessary files with content, git repository and venv.
Author-email: Philipp Meder <148459685+PhilippMeder@users.noreply.github.com>
Maintainer-email: Philipp Meder <148459685+PhilippMeder@users.noreply.github.com>
License: BSD 3-Clause License
Project-URL: Changelog, https://github.com/PhilippMeder/pkgcreator/blob/main/CHANGELOG.md
Project-URL: Documentation, https://github.com/PhilippMeder/pkgcreator#readme
Project-URL: Download, https://github.com/PhilippMeder/pkgcreator
Project-URL: Homepage, https://github.com/PhilippMeder/pkgcreator
Project-URL: Issues, https://github.com/PhilippMeder/pkgcreator/issues
Project-URL: Releasenotes, https://github.com/PhilippMeder/pkgcreator/releases
Project-URL: Source, https://github.com/PhilippMeder/pkgcreator.git
Keywords: python,packaging,project-setup,cli,automation
Classifier: Intended Audience :: Developers
Classifier: License :: OSI Approved :: BSD License
Classifier: Operating System :: OS Independent
Classifier: Programming Language :: Python :: 3
Classifier: Programming Language :: Python :: 3.10
Classifier: Programming Language :: Python :: 3.11
Classifier: Programming Language :: Python :: 3.12
Classifier: Programming Language :: Python :: 3.13
Classifier: Topic :: Software Development
Classifier: Topic :: Software Development :: Version Control :: Git
Classifier: Topic :: System :: Archiving :: Packaging
Classifier: Topic :: System :: Software Distribution
Requires-Python: >=3.10
License-File: LICENSE
Provides-Extra: full
Requires-Dist: requests; extra == "full"
Provides-Extra: dev
Requires-Dist: pytest; extra == "dev"
Requires-Dist: ruff; extra == "dev"
Dynamic: license-file
